chararray/__init__.py
chararray-1.0.1.dist-info/LICENSE
chararray-1.0.1.dist-info/METADATA
chararray-1.0.1.dist-info/WHEEL
chararray-1.0.1.dist-info/top_level.txt
chararray-1.0.1.dist-info/RECORD
